pure/__init__.py
pure/colors.py
pure/prompt.py
tests/__init__.py
tests/colors_test.py
tests/prompt_test.py
pure-2.0.0.dist-info/LICENSE
pure-2.0.0.dist-info/METADATA
pure-2.0.0.dist-info/WHEEL
pure-2.0.0.dist-info/top_level.txt
pure-2.0.0.dist-info/RECORD
