Metadata-Version: 2.1
Name: pure
Version: 2.0.0
Summary: Pretty, minimal and fast prompt for various shells
Home-page: https://github.com/edouard-lopez/pure
Author: Édouard Lopez
Author-email: contact@edouard-lopez.com
License: UNKNOWN
Platform: UNKNOWN
Classifier: Topic :: System :: Shells
Classifier: Operating System :: OS Independent
Classifier: Intended Audience :: Developers
Classifier: Intended Audience :: End Users/Desktop
Classifier: Operating System :: POSIX
Classifier: Natural Language :: English
Classifier: Topic :: Terminals
Classifier: Environment :: Console
Classifier: Programming Language :: Python :: 3
Classifier: License :: OSI Approved :: MIT License
